messenger_business_api/__init__.py
messenger_business_api/api.py
messenger_business_api/execeptions.py
messenger_business_api/types.py
messenger_business_api-1.0.5.dist-info/LICENSE
messenger_business_api-1.0.5.dist-info/METADATA
messenger_business_api-1.0.5.dist-info/WHEEL
messenger_business_api-1.0.5.dist-info/top_level.txt
messenger_business_api-1.0.5.dist-info/RECORD
